MANIFEST.in
README.md
iz.conf
setup.py
Chrome/__init__.py
Chrome/chrome.py
Core/Logger.py
Core/TimeoutManager.py
Core/__init__.py
Core/izHelpers.py
Core/selenium_wrapper.py
Core/session_manager.py
data/sessions.json
izSelenium.egg-info/PKG-INFO
izSelenium.egg-info/SOURCES.txt
izSelenium.egg-info/dependency_links.txt
izSelenium.egg-info/requires.txt
izSelenium.egg-info/top_level.txt