Metadata-Version: 2.1
Name: izSelenium
Version: 1.0.0
Summary: a decent selenium wrapper
Home-page: https://github.com/MrPupik/izSelenium
Author: Itay Zohar
Author-email: itaynzohar@gmail.com
License: MIT
Platform: UNKNOWN
Classifier: License :: OSI Approved :: MIT License
Classifier: Programming Language :: Python :: 3
Classifier: Programming Language :: Python :: 3.8
